[
    {
        "Affiliation": "Meghalaya Cooperative Apex Bank Ltd. (M.C.A.B. Ltd.)"
    },
    {
        "Affiliation": "Meghalaya Rural Tourism  Coop. Federation Ltd. (M.R.T.C.F. Ltd)"
    },
    {
        "Affiliation": "Eastern Region Marketing Cooperative Society Ltd. (EaRMaCS Ltd.)"
    },
    {
        "Affiliation": "Meghalaya State Cooperative Marketing & Consumers’ Federation Ltd. (M.E.C.O.F.E.D. Ltd.)"
    },
    {
        "Affiliation": "Meghalaya State Housing Financing Cooperative Society Ltd. (M.S.H.F.C.S. Ltd.)"
    },
    {
        "Affiliation": "Meghalaya Apex Handloom Weavers & Handicrafts Cooperative Federation Ltd. (M.E.G.H.A.L.O.O.M. Ltd.)"
    },
    {
        "Affiliation": "Meghalaya State Fisheries Cooperative  Federation Ltd. "
    },
    {
        "Affiliation": "CONSERVATION, RESEARCH & DEVELOPMENT (LIVING ROOT BRIDGES) Syrwet Uba Rim Mariang Jingkieng Jri  Coop. Federation Ltd."
    },
    {
        "Affiliation": "Meghalaya State Cooperative Union Ltd. (M.S.C.U. Ltd.)"
    },
    {
        "Affiliation": "Meghalaya Livestock & Dairy Cooperative  Federation Ltd. "
    },
    {
        "Affiliation": " Mei Ramew State Agroecology Cooperative Society Ltd."
    }
]